wyrmx_cli/commands/__init__.py
wyrmx_cli/commands/database_management/__init__.py
wyrmx_cli/commands/database_management/edit.py
wyrmx_cli/commands/database_management/make_migration.py
wyrmx_cli/commands/database_management/migrate.py
wyrmx_cli/commands/database_management/rollback.py
wyrmx_cli/commands/file_generators/__init__.py
wyrmx_cli/commands/file_generators/generate_controller/__init__.py
wyrmx_cli/commands/file_generators/generate_controller/create_controller_folder.py
wyrmx_cli/commands/file_generators/generate_controller/create_root_controller_folder.py
wyrmx_cli/commands/file_generators/generate_controller/generate_controller.py
wyrmx_cli/commands/file_generators/generate_model/__init__.py
wyrmx_cli/commands/file_generators/generate_model/create_model_folder.py
wyrmx_cli/commands/file_generators/generate_model/create_root_model_folder.py
wyrmx_cli/commands/file_generators/generate_model/generate_model.py
wyrmx_cli/commands/file_generators/generate_payload.py
wyrmx_cli/commands/file_generators/generate_response.py
wyrmx_cli/commands/file_generators/generate_schema.py
wyrmx_cli/commands/file_generators/generate_service/__init__.py
wyrmx_cli/commands/file_generators/generate_service/create_root_service_folder.py
wyrmx_cli/commands/file_generators/generate_service/create_service_folder.py
wyrmx_cli/commands/file_generators/generate_service/generate_service.py
wyrmx_cli/commands/new.py
wyrmx_cli/commands/run.py
wyrmx_cli/commands/serve.py
wyrmx_cli/commands/test.py
wyrmx_cli/commands/version.py
wyrmx_cli/commands/vibe.py
wyrmx_cli/main.py
wyrmx_cli/utilities/env_utilities/__init__.py
wyrmx_cli/utilities/env_utilities/check_workspace.py
wyrmx_cli/utilities/file_utilities/__init__.py
wyrmx_cli/utilities/file_utilities/create_file.py
wyrmx_cli/utilities/file_utilities/file_exists.py
wyrmx_cli/utilities/file_utilities/insert_line.py
wyrmx_cli/utilities/file_utilities/replace_line.py
wyrmx_cli/utilities/string_utilities/__init__.py
wyrmx_cli-1.0.119.dist-info/METADATA
wyrmx_cli-1.0.119.dist-info/WHEEL
wyrmx_cli-1.0.119.dist-info/entry_points.txt
wyrmx_cli-1.0.119.dist-info/RECORD
