Metadata-Version: 2.3
Name: wyrmx-cli
Version: 1.0.119
Summary: Wyrmx CLI is the official command-line interface for Wyrmx — a blazing-fast, Cython-accelerated, AI-enhanced web framework built on FastAPI.
License: MIT
Author: Yousri Aouledissa
Author-email: aouledissayousri@gmail.com
Requires-Python: >=3.13,<4.0
Classifier: License :: OSI Approved :: MIT License
Classifier: Programming Language :: Python :: 3
Classifier: Programming Language :: Python :: 3.13
Requires-Dist: azure-ai-inference (>=1.0.0b9,<2.0.0)
Requires-Dist: azure-core (>=1.38.0,<2.0.0)
Requires-Dist: build (>=1.2.2.post1,<2.0.0)
Requires-Dist: distlib (>=0.3.9,<0.4.0)
Requires-Dist: dulwich (>=0.22.8,<0.23.0)
Requires-Dist: filelock (>=3.18.0,<4.0.0)
Requires-Dist: huggingface-hub (>=1.3.2,<2.0.0)
Requires-Dist: packaging (>=25.0,<26.0)
Requires-Dist: poetry (>=2.1.3,<3.0.0)
Requires-Dist: poetry-core (>=2.1.3,<3.0.0)
Requires-Dist: shellingham (>=1.5.4,<2.0.0)
Requires-Dist: tomlkit (>=0.13.2,<0.14.0)
Requires-Dist: typer (>=0.16.0,<0.17.0)
Requires-Dist: virtualenv (>=20.31.2,<21.0.0)
